{
  "sections": {
    "8bcb72a6-a9a0-4ffe-83c3-adea50266c35": {
      "type": "hero-video",
      "settings": {
        "title": "WATCH THE LIVE STREAM OF OUR DRAW HERE AT 5PM EST TODAY!",
        "title_size": 70,
        "subheading": "GOOD LUCK FROM ALL OF MOTA TEAM!",
        "link_text": "Click for sound",
        "link": "#play-sound",
        "color_accent": "#000000",
        "text_align": "vertical-center horizontal-center",
        "video_url": "https:\/\/cdn.shopify.com\/videos\/c\/o\/v\/89363cff6d9f49fa9049e57cce5d54fe.mp4",
        "section_height": "100vh",
        "mobile_height": "500px"
      }
    },
    "marquee": {
      "type": "marquee",
      "disabled": true,
      "settings": {
        "text": "Our Current Giveaway, 1978 Porsche 930 Turbo",
        "link": "shopify:\/\/pages\/vip-club",
        "text_size": 20,
        "text_spacing": true,
        "color_scheme": "button",
        "direction": "left",
        "speed": "slow"
      }
    },
    "text-and-image": {
      "type": "text-and-image",
      "settings": {
        "image": "shopify:\/\/shop_images\/1.png",
        "image2": "shopify:\/\/shop_images\/latest_staff.png",
        "image_width": 700,
        "subtitle": "",
        "title": "Welcome to Mota",
        "text": "<p>Mota is a membership rewards club for car lovers offering discounts and savings across our retail platform, as well as giving you the opportunity to win classic and rare cars through our member giveaways. <\/p><p>Our current giveaway is one of our all time favourites! A 1978 Porsche 930 Turbo. Our next giveaway is a 1967 Ford Mustang Fastback. <\/p><p>Mota giveaways offer our members the absolute best classics and some of the most collectible cars available. If you are a car lover, car collector, or just want a really cool car to drive to work or on weekends, then this is the membership club for you. <\/p><p>Purchase a single one off membership for your chance to win a particular car giveaway, or a VIP membership that accumulates your entries each month for the best chance to win in all of our giveaways. VIP Members are automatically entered into every car giveaway.  <\/p><p>We hope you enjoy all the benefits of becoming a member. <\/p><p>Safe and enjoyable motoring from the Mota Team;  Jordan, Jasmine, Luke, Shane + Dylan. <\/p>",
        "button_label": "",
        "button_link": "shopify:\/\/pages\/vip-club",
        "button_style": "secondary",
        "align_text": "left",
        "layout": "right",
        "alt": false
      }
    },
    "0cce90cc-b19b-48df-979a-543cf061d842": {
      "type": "hero-animated",
      "blocks": {
        "template--14857727705181__0cce90cc-b19b-48df-979a-543cf061d842-1669588561906fb567-1": {
          "type": "image",
          "settings": {
            "image": "shopify:\/\/shop_images\/OUR_PORSCHE_DRAW_IS_NOW_CLOSED..png",
            "image_mobile": "shopify:\/\/shop_images\/OUR_PORSCHE_DRAW_IS_NOW_CLOSED._Instagram_Story_1.png",
            "focal_point": "center center"
          }
        }
      },
      "block_order": [
        "template--14857727705181__0cce90cc-b19b-48df-979a-543cf061d842-1669588561906fb567-1"
      ],
      "settings": {
        "style": "gif",
        "title": "",
        "title_size": 80,
        "subheading": "",
        "link": "",
        "link_text": "",
        "color_accent": "rgba(0,0,0,0)",
        "text_align": "vertical-center horizontal-center",
        "desktop_size": 0,
        "mobile_size": 0
      }
    },
    "165465702668704949": {
      "type": "background-image-text",
      "disabled": true,
      "settings": {
        "subtitle": "Our current giveaway",
        "title": "1978 Porsche 930 Turbo",
        "text": "<p>6 cylinder | 3.3Ltr Turbo engine  | Racing bucket seats    | 4 speed manual gearbox  | Widebody GT2 body kit       |        |Racing bonnet and engine clips |               <\/p><p><strong>Valued at  $205,000!<\/strong><\/p><p>Permit Number: TP\/01963<\/p><p>Promotion capped at 8,000 total entrants. Draw takes place on 15\/12\/2022 or earlier if cap is reached. The draw is guaranteed. <\/p><p>The number of total entrants registered is displayed on our 'Giveaways Page' updated daily.<\/p><p>The draw is overseen by an external scrutineer, not affiliated with our company. The Scrutineer is qualified as a Notary Public, Justice of the Peace and is a current practicing Barrister and Solictor. <\/p>",
        "button_label": "GET ENTRIES",
        "button_link": "shopify:\/\/pages\/giveaway",
        "image": "shopify:\/\/shop_images\/999.png",
        "desktop_size": 0,
        "image_alignment": "center center",
        "color_border": "#f4f4f4",
        "layout": "left"
      }
    },
    "1653981611f18a881e": {
      "type": "text-with-icons",
      "blocks": {
        "165398161197938c5e-0": {
          "type": "text_block",
          "settings": {
            "icon": "cart",
            "title": "BUY YOUR ENTRIES",
            "text": "<p>Purchase a single entry membership OR a VIP Monthly Membership to win the cars! <\/p>"
          }
        },
        "165398161197938c5e-1": {
          "type": "text_block",
          "settings": {
            "icon": "sales-tag",
            "title": "SHOP AND SAVE",
            "text": "<p>Receive discounts and offers across our automotive + retail  partner network. Mota gives you access to incredible savings with access to thousands of offers from Australia's most popular retailers and automative specialists, offers that are not available to the general public.<\/p>"
          }
        },
        "165398161197938c5e-2": {
          "type": "text_block",
          "settings": {
            "icon": "charity",
            "title": "Support the Royal Melbourne childrens hospital",
            "text": "<p>Help us continue to suport & donate to our favourite charites. Mota team has partnered with the Royal Melbourne Childrens Hosptial and is currently sponsoring a bed in their Kookaburra Ward for kids battling cancer. <\/p>"
          }
        }
      },
      "block_order": [
        "165398161197938c5e-0",
        "165398161197938c5e-1",
        "165398161197938c5e-2"
      ],
      "settings": {
        "title": "how it works",
        "align_text": "center",
        "desktop_columns_per_row": 3,
        "icon_color": "#000000",
        "button_label": "",
        "button_link": "",
        "alt": false
      }
    },
    "1655180449ae267329": {
      "type": "featured-membership",
      "disabled": true,
      "settings": {
        "title": "join our vip now",
        "description": "The best part about becoming a VIP member is that is pays for itself, plus some... Mota gives you access to incredible savings and offers from over 4,000 Australian brands + retailers, offers and discounts that are not available to the general public. Once a VIP package is purchased, simply login as a member to access. VIP members receive entries into every single giveaway, your entries accumulate each month giving you the best chance to win!",
        "home_featured_products": "vip-memberships",
        "rows": 2,
        "per_row_desktop": 3,
        "per_row_mobile": "1",
        "display_button": false,
        "alt": false
      }
    },
    "featured-collection": {
      "type": "featured-collection",
      "disabled": true,
      "settings": {
        "title": "or GET YOUR SINGLE ENTRY Membership NOW!",
        "description": "One time payment only. Giveaway Permit Number: TP\/01963",
        "home_featured_products": "ticket-entries",
        "rows": 2,
        "per_row_desktop": 3,
        "per_row_mobile": "2-flush",
        "view_all": false,
        "alt": false
      }
    },
    "165448555898d0b98d": {
      "type": "text-and-image",
      "settings": {
        "image": "shopify:\/\/shop_images\/RCHF.png",
        "image2": "shopify:\/\/shop_images\/Kookaburra.png",
        "image_width": 610,
        "subtitle": "",
        "title": "CHARITIES WE LOVE + SUPPORT",
        "text": "<p>MOTA team couldn't be more proud to be sponsoring a bed at the Royal Melbourne Children's Hospital, in the Kookaburra Ward for children battling cancer. Mota will be sponsoring additional bed's at the Children's Hospital for every new member car giveaway we run. <\/p><p>We are excited to help support in this way to the amazing work the team at the Children's Hospital are doing. They are absolute angels! <\/p><p><br\/><\/p>",
        "button_label": "",
        "button_link": "",
        "button_style": "primary",
        "align_text": "left",
        "layout": "left",
        "alt": false
      }
    },
    "16564991630da22a6d": {
      "type": "text-and-image",
      "settings": {
        "image": "shopify:\/\/shop_images\/bbb.png",
        "image2": "shopify:\/\/shop_images\/Shelby_1.png",
        "image_width": 700,
        "subtitle": "Our next Giveaway",
        "title": "1967 FORD MUSTANG fastback",
        "text": "<p>Check out our 'Future Giveaways' page for information on our next giveaway. Entry for the Mustang will open at the conculsion of our Porsche Turbo draw. All draws are streamed live on facebook and socials. Become a VIP member today to be automatically entered into every giveaway, including this Mustang Fastback, you won't miss out!<\/p>",
        "button_label": "",
        "button_link": "",
        "button_style": "primary",
        "align_text": "center",
        "layout": "right",
        "alt": false
      }
    },
    "71e63ad1-e6b0-495c-a409-080e406ef502": {
      "type": "background-image-text",
      "settings": {
        "subtitle": "",
        "title": "",
        "text": "",
        "button_label": "",
        "button_link": "",
        "image": "shopify:\/\/shop_images\/5555.png",
        "desktop_size": 0,
        "image_alignment": "center center",
        "color_border": "#f4f4f4",
        "layout": "left"
      }
    },
    "1654498494af01ade5": {
      "type": "marquee",
      "settings": {
        "text": "FOLLOW US ON INSTAGRAM @Motateamaustralia",
        "link": "",
        "text_size": 30,
        "text_spacing": true,
        "color_scheme": "button",
        "direction": "left",
        "speed": "slow"
      }
    },
    "2c0c229b_1663023414": {
      "type": "powr-video-slider",
      "settings": {
      }
    },
    "165448950900f21cf3": {
      "type": "apps",
      "blocks": {
        "bfb596c7-91ec-460e-afb2-5c5d2d04e37b": {
          "type": "shopify:\/\/apps\/instafeed-instagram-feed\/blocks\/app-block\/c447db20-095d-4a10-9725-b5977662c9d5",
          "settings": {
            "heading_size": 25,
            "feed_width": 100,
            "html_area": ""
          }
        }
      },
      "block_order": [
        "bfb596c7-91ec-460e-afb2-5c5d2d04e37b"
      ],
      "settings": {
        "full_width": false,
        "space_around": true
      }
    },
    "165449668147bb6440": {
      "type": "apps",
      "settings": {
        "full_width": false,
        "space_around": true
      }
    },
    "1661816998a3fed132": {
      "type": "MBA",
      "blocks": {
        "1661816997cbdfa36e-0": {
          "type": "image",
          "settings": {
            "image": "shopify:\/\/shop_images\/VIP1.png",
            "focal_point": "center center"
          }
        },
        "1661816997cbdfa36e-1": {
          "type": "image",
          "settings": {
            "focal_point": "center center"
          }
        }
      },
      "block_order": [
        "1661816997cbdfa36e-0",
        "1661816997cbdfa36e-1"
      ],
      "settings": {
        "style": "gif",
        "title": "",
        "title_size": 30,
        "subheading": "Login to Members Portal here when signed in as a member",
        "link": "",
        "link_text": "Benefits Login",
        "color_accent": "rgba(0,0,0,0)",
        "text_align": "vertical-center horizontal-center",
        "desktop_size": -30,
        "mobile_size": 0
      }
    }
  },
  "order": [
    "8bcb72a6-a9a0-4ffe-83c3-adea50266c35",
    "marquee",
    "text-and-image",
    "0cce90cc-b19b-48df-979a-543cf061d842",
    "165465702668704949",
    "1653981611f18a881e",
    "1655180449ae267329",
    "featured-collection",
    "165448555898d0b98d",
    "16564991630da22a6d",
    "71e63ad1-e6b0-495c-a409-080e406ef502",
    "1654498494af01ade5",
    "2c0c229b_1663023414",
    "165448950900f21cf3",
    "165449668147bb6440",
    "1661816998a3fed132"
  ]
}
